README.txt
setup.py
upload_dnatools_2/__init__.py
upload_dnatools_2/at_content.py
upload_dnatools_2.egg-info/PKG-INFO
upload_dnatools_2.egg-info/SOURCES.txt
upload_dnatools_2.egg-info/dependency_links.txt
upload_dnatools_2.egg-info/top_level.txt